__init__.py
cj_tools/__init__.py
cj_tools/date_formatting.py
cj_tools/log.py
cj_tools/mysql_operate.py
cj_tools-0.1.1.dist-info/LICENSE
cj_tools-0.1.1.dist-info/METADATA
cj_tools-0.1.1.dist-info/WHEEL
cj_tools-0.1.1.dist-info/top_level.txt
cj_tools-0.1.1.dist-info/RECORD
