Metadata-Version: 2.1
Name: cj-tools
Version: 0.1.1
Summary: Some useful and common tools.
Author-email: cwj <17800372351@163.com>
License: MIT License        
Keywords: cj,tools
License-File: LICENSE
